my_bmi_project/calculate_bmi.py
my_bmi_project-0.0.0.2.dist-info/METADATA
my_bmi_project-0.0.0.2.dist-info/WHEEL
my_bmi_project-0.0.0.2.dist-info/top_level.txt
my_bmi_project-0.0.0.2.dist-info/RECORD
